nonebot_plugin_bfinfo/STXINGKA.TTF
nonebot_plugin_bfinfo/__init__.py
nonebot_plugin_bfinfo/bf_translate.json
nonebot_plugin_bfinfo/general_bg.jpg
nonebot_plugin_bfinfo/bf1/class_img/Assault.png
nonebot_plugin_bfinfo/bf1/class_img/Cavalry.png
nonebot_plugin_bfinfo/bf1/class_img/Medic.png
nonebot_plugin_bfinfo/bf1/class_img/Pilot.png
nonebot_plugin_bfinfo/bf1/class_img/Scout.png
nonebot_plugin_bfinfo/bf1/class_img/Support.png
nonebot_plugin_bfinfo/bf1/class_img/Tanker.png
nonebot_plugin_bfinfo/bf1/vehicle_img/Airship/C-class airship.png
nonebot_plugin_bfinfo/bf1/vehicle_img/Artillery truck/Artillery truck.png
nonebot_plugin_bfinfo/bf1/vehicle_img/Assault tank/St chamond.png
nonebot_plugin_bfinfo/bf1/vehicle_img/Assault truck/Putilov garford.png
nonebot_plugin_bfinfo/bf1/vehicle_img/Attack plane/A.e.f 2-a2 attack plane.png
nonebot_plugin_bfinfo/bf1/vehicle_img/Attack plane/Bristol f2.b attack plane.png
nonebot_plugin_bfinfo/bf1/vehicle_img/Attack plane/Halberstadt cl. ii attack plane.png
nonebot_plugin_bfinfo/bf1/vehicle_img/Attack plane/Rumpler c.i attack plane.png
nonebot_plugin_bfinfo/bf1/vehicle_img/Behemoth/Airship l30.png
nonebot_plugin_bfinfo/bf1/vehicle_img/Behemoth/Armored train.png
nonebot_plugin_bfinfo/bf1/vehicle_img/Behemoth/Char 2c.png
nonebot_plugin_bfinfo/bf1/vehicle_img/Behemoth/Dreadnought.png
nonebot_plugin_bfinfo/bf1/vehicle_img/Boat/M.a.s. torpedo boat.png
nonebot_plugin_bfinfo/bf1/vehicle_img/Boat/Y lighter landing craft.png
nonebot_plugin_bfinfo/bf1/vehicle_img/Bomber/Airco dh.10.png
nonebot_plugin_bfinfo/bf1/vehicle_img/Bomber/Caproni ca.5 bomber.png
nonebot_plugin_bfinfo/bf1/vehicle_img/Bomber/Gotha g.iv bomber.png
nonebot_plugin_bfinfo/bf1/vehicle_img/Bomber/Hansa-brandenburg g.i.png
nonebot_plugin_bfinfo/bf1/vehicle_img/Destroyer/L-class destroyer.png
nonebot_plugin_bfinfo/bf1/vehicle_img/Fighter/Albatros diii  fighter.png
nonebot_plugin_bfinfo/bf1/vehicle_img/Fighter/Dr.1 fighter.png
nonebot_plugin_bfinfo-0.0.5.dist-info/LICENSE
nonebot_plugin_bfinfo-0.0.5.dist-info/METADATA
nonebot_plugin_bfinfo-0.0.5.dist-info/WHEEL
nonebot_plugin_bfinfo-0.0.5.dist-info/top_level.txt
nonebot_plugin_bfinfo-0.0.5.dist-info/RECORD
