Metadata-Version: 2.1
Name: nonebot-plugin-bfinfo
Version: 0.0.5
Summary: nonebot plugin bfinfo
Home-page: https://github.com/GC-ZF/nonebot_plugin_bfinfo
Author: zhangshier
Author-email: 1310446718@qq.com
Keywords: pip,nonebot2,nonebot,battlefield,nonebot_plugin
Platform: any
Classifier: Programming Language :: Python :: 3
Classifier: License :: OSI Approved :: MIT License
Classifier: Operating System :: OS Independent
Requires-Python: >=3.7.3,<4.0
License-File: LICENSE
Requires-Dist: nonebot2 (>=2.0.0-beta.4)
Requires-Dist: nonebot-adapter-onebot (>=2.0.0-beta.1)
Requires-Dist: matplotlib (>=3.6.2)
Requires-Dist: Pillow (>=9.3.0)
Requires-Dist: requests (>=2.28.1)
